.gitignore
MANIFEST.in
README.rst
setup.cfg
setup.py
docs/HISTORY.txt
docs/LICENSE.GPL
docs/LICENSE.txt
docs/MANUAL.txt
raptus/__init__.py
raptus.article.additionalwysiwyg.egg-info/PKG-INFO
raptus.article.additionalwysiwyg.egg-info/SOURCES.txt
raptus.article.additionalwysiwyg.egg-info/dependency_links.txt
raptus.article.additionalwysiwyg.egg-info/entry_points.txt
raptus.article.additionalwysiwyg.egg-info/namespace_packages.txt
raptus.article.additionalwysiwyg.egg-info/not-zip-safe
raptus.article.additionalwysiwyg.egg-info/requires.txt
raptus.article.additionalwysiwyg.egg-info/top_level.txt
raptus/article/__init__.py
raptus/article/additionalwysiwyg/__init__.py
raptus/article/additionalwysiwyg/configure.zcml
raptus/article/additionalwysiwyg/extender.py
raptus/article/additionalwysiwyg/interfaces.py
raptus/article/additionalwysiwyg/wysiwyg.py
raptus/article/additionalwysiwyg/browser/__init__.py
raptus/article/additionalwysiwyg/browser/configure.zcml
raptus/article/additionalwysiwyg/browser/wysiwyg.pt
raptus/article/additionalwysiwyg/browser/wysiwyg.py
raptus/article/additionalwysiwyg/browser/wysiwyg_bottom.gif
raptus/article/additionalwysiwyg/browser/wysiwyg_full.gif
raptus/article/additionalwysiwyg/browser/wysiwyg_left.gif
raptus/article/additionalwysiwyg/browser/wysiwyg_right.gif
raptus/article/additionalwysiwyg/browser/wysiwyg_top.gif
raptus/article/additionalwysiwyg/i18n/raptus.article-de.mo
raptus/article/additionalwysiwyg/i18n/raptus.article-de.po
raptus/article/additionalwysiwyg/i18n/raptus.article-fr.mo
raptus/article/additionalwysiwyg/i18n/raptus.article-fr.po
raptus/article/additionalwysiwyg/i18n/raptus.article.pot
raptus/article/additionalwysiwyg/profiles/default/cssregistry.xml
raptus/article/additionalwysiwyg/profiles/default/metadata.xml
raptus/article/additionalwysiwyg/profiles/default/propertiestool.xml
raptus/article/additionalwysiwyg/profiles/default/skins.xml
raptus/article/additionalwysiwyg/profiles/default/viewlets.xml
raptus/article/additionalwysiwyg/skins/raptus_article_additionalwysiwyg/raptus.article.additionalwysiwyg.css.dtml