Metadata-Version: 1.1
Name: raptus.article.additionalwysiwyg
Version: 2.0b7
Summary: Provides an additional WYSIWYG text field for the articles.
Home-page: https://github.com/Raptus/raptus.article.additionalwysiwyg
Author: Raptus AG
Author-email: dev@raptus.com
License: GPL
Platform: UNKNOWN
Classifier: Programming Language :: Python
Classifier: Topic :: Software Development :: Libraries :: Python Modules
